{
  "_id": {
    "$oid": "58f94c382c8d1f3958ccf052"
  }, 
  "coordinateSystem": "GEO", 
  "duration": 596.0, 
  "endTime": 1492073953.0, 
  "haveAltitude": false, 
  "locked": false, 
  "name": "2017-04-12_17-49-14", 
  "recs": [
    {
      "pos": [
        37.32509939, 
        -122.04549899, 
        50.0
      ], 
      "rt": 0.0, 
      "time": 1492073357.0
    }, 
    {
      "pos": [
        37.32510004, 
        -122.04549993, 
        50.0
      ], 
      "rt": 1.0, 
      "time": 1492073358.0
    }, 
    {
      "pos": [
        37.32510053, 
        -122.04549906, 
        50.0
      ], 
      "rt": 2.0, 
      "time": 1492073359.0
    }, 
    {
      "pos": [
        37.32510125, 
        -122.04549793, 
        50.0
      ], 
      "rt": 3.0, 
      "time": 1492073360.0
    }, 
    {
      "pos": [
        37.32510209, 
        -122.04549734, 
        50.0
      ], 
      "rt": 4.0, 
      "time": 1492073361.0
    }, 
    {
      "pos": [
        37.32510302, 
        -122.04549709, 
        49.0
      ], 
      "rt": 5.0, 
      "time": 1492073362.0
    }, 
    {
      "pos": [
        37.32510358, 
        -122.04549729, 
        49.0
      ], 
      "rt": 6.0, 
      "time": 1492073363.0
    }, 
    {
      "pos": [
        37.32510457, 
        -122.04549849, 
        49.0
      ], 
      "rt": 7.0, 
      "time": 1492073364.0
    }, 
    {
      "pos": [
        37.32510563, 
        -122.04549966, 
        49.0
      ], 
      "rt": 8.0, 
      "time": 1492073365.0
    }, 
    {
      "pos": [
        37.32510571, 
        -122.04550024, 
        49.0
      ], 
      "rt": 9.0, 
      "time": 1492073366.0
    }, 
    {
      "pos": [
        37.32510556, 
        -122.04550065, 
        49.0
      ], 
      "rt": 10.0, 
      "time": 1492073367.0
    }, 
    {
      "pos": [
        37.32510543, 
        -122.04550097, 
        49.0
      ], 
      "rt": 11.0, 
      "time": 1492073368.0
    }, 
    {
      "pos": [
        37.3251053, 
        -122.04550113, 
        49.0
      ], 
      "rt": 12.0, 
      "time": 1492073369.0
    }, 
    {
      "pos": [
        37.32510524, 
        -122.04550116, 
        49.0
      ], 
      "rt": 13.0, 
      "time": 1492073370.0
    }, 
    {
      "pos": [
        37.32510521, 
        -122.04550117, 
        49.0
      ], 
      "rt": 14.0, 
      "time": 1492073371.0
    }, 
    {
      "pos": [
        37.3251052, 
        -122.04550118, 
        49.0
      ], 
      "rt": 15.0, 
      "time": 1492073372.0
    }, 
    {
      "pos": [
        37.32510519, 
        -122.04550117, 
        49.0
      ], 
      "rt": 16.0, 
      "time": 1492073373.0
    }, 
    {
      "pos": [
        37.32510519, 
        -122.04550116, 
        49.0
      ], 
      "rt": 17.0, 
      "time": 1492073374.0
    }, 
    {
      "pos": [
        37.32510518, 
        -122.04550114, 
        49.0
      ], 
      "rt": 18.0, 
      "time": 1492073375.0
    }, 
    {
      "pos": [
        37.32510518, 
        -122.04550113, 
        49.0
      ], 
      "rt": 19.0, 
      "time": 1492073376.0
    }, 
    {
      "pos": [
        37.32510518, 
        -122.0455011, 
        49.0
      ], 
      "rt": 20.0, 
      "time": 1492073377.0
    }, 
    {
      "pos": [
        37.32510518, 
        -122.04550109, 
        49.0
      ], 
      "rt": 21.0, 
      "time": 1492073378.0
    }, 
    {
      "pos": [
        37.32510518, 
        -122.04550107, 
        49.0
      ], 
      "rt": 22.0, 
      "time": 1492073379.0
    }, 
    {
      "pos": [
        37.32510518, 
        -122.04550106, 
        49.0
      ], 
      "rt": 23.0, 
      "time": 1492073380.0
    }, 
    {
      "pos": [
        37.32510518, 
        -122.04550105, 
        49.0
      ], 
      "rt": 24.0, 
      "time": 1492073381.0
    }, 
    {
      "pos": [
        37.32510517, 
        -122.04550104, 
        49.0
      ], 
      "rt": 25.0, 
      "time": 1492073382.0
    }, 
    {
      "pos": [
        37.32510516, 
        -122.04550103, 
        49.0
      ], 
      "rt": 26.0, 
      "time": 1492073383.0
    }, 
    {
      "pos": [
        37.32510516, 
        -122.04550103, 
        49.0
      ], 
      "rt": 27.0, 
      "time": 1492073384.0
    }, 
    {
      "pos": [
        37.32510516, 
        -122.04550102, 
        49.0
      ], 
      "rt": 28.0, 
      "time": 1492073385.0
    }, 
    {
      "pos": [
        37.32510516, 
        -122.04550101, 
        49.0
      ], 
      "rt": 29.0, 
      "time": 1492073386.0
    }, 
    {
      "pos": [
        37.32510516, 
        -122.045501, 
        49.0
      ], 
      "rt": 30.0, 
      "time": 1492073387.0
    }, 
    {
      "pos": [
        37.32510514, 
        -122.04550098, 
        49.0
      ], 
      "rt": 31.0, 
      "time": 1492073388.0
    }, 
    {
      "pos": [
        37.32510513, 
        -122.04550097, 
        49.0
      ], 
      "rt": 32.0, 
      "time": 1492073389.0
    }, 
    {
      "pos": [
        37.32510512, 
        -122.04550096, 
        49.0
      ], 
      "rt": 33.0, 
      "time": 1492073390.0
    }, 
    {
      "pos": [
        37.32510511, 
        -122.04550095, 
        49.0
      ], 
      "rt": 34.0, 
      "time": 1492073391.0
    }, 
    {
      "pos": [
        37.32510511, 
        -122.04550095, 
        49.0
      ], 
      "rt": 35.0, 
      "time": 1492073392.0
    }, 
    {
      "pos": [
        37.3251051, 
        -122.04550097, 
        49.0
      ], 
      "rt": 36.0, 
      "time": 1492073393.0
    }, 
    {
      "pos": [
        37.3251051, 
        -122.04550098, 
        49.0
      ], 
      "rt": 37.0, 
      "time": 1492073394.0
    }, 
    {
      "pos": [
        37.32510509, 
        -122.04550099, 
        49.0
      ], 
      "rt": 38.0, 
      "time": 1492073395.0
    }, 
    {
      "pos": [
        37.32510509, 
        -122.045501, 
        49.0
      ], 
      "rt": 39.0, 
      "time": 1492073396.0
    }, 
    {
      "pos": [
        37.3251051, 
        -122.04550101, 
        49.0
      ], 
      "rt": 40.0, 
      "time": 1492073397.0
    }, 
    {
      "pos": [
        37.3251051, 
        -122.04550102, 
        49.0
      ], 
      "rt": 41.0, 
      "time": 1492073398.0
    }, 
    {
      "pos": [
        37.32510442, 
        -122.04550453, 
        49.0
      ], 
      "rt": 42.0, 
      "time": 1492073399.0
    }, 
    {
      "pos": [
        37.32510344, 
        -122.04551269, 
        50.0
      ], 
      "rt": 43.0, 
      "time": 1492073400.0
    }, 
    {
      "pos": [
        37.32510234, 
        -122.04552526, 
        50.0
      ], 
      "rt": 44.0, 
      "time": 1492073401.0
    }, 
    {
      "pos": [
        37.32510137, 
        -122.04554028, 
        50.0
      ], 
      "rt": 45.0, 
      "time": 1492073402.0
    }, 
    {
      "pos": [
        37.32509957, 
        -122.04555532, 
        51.0
      ], 
      "rt": 46.0, 
      "time": 1492073403.0
    }, 
    {
      "pos": [
        37.32509898, 
        -122.04556961, 
        50.0
      ], 
      "rt": 47.0, 
      "time": 1492073404.0
    }, 
    {
      "pos": [
        37.325099, 
        -122.04558495, 
        51.0
      ], 
      "rt": 48.0, 
      "time": 1492073405.0
    }, 
    {
      "pos": [
        37.3250997, 
        -122.04560118, 
        51.0
      ], 
      "rt": 49.0, 
      "time": 1492073406.0
    }, 
    {
      "pos": [
        37.32510104, 
        -122.04561636, 
        52.0
      ], 
      "rt": 50.0, 
      "time": 1492073407.0
    }, 
    {
      "pos": [
        37.32510432, 
        -122.04563137, 
        51.0
      ], 
      "rt": 51.0, 
      "time": 1492073408.0
    }, 
    {
      "pos": [
        37.32510803, 
        -122.04564552, 
        51.0
      ], 
      "rt": 52.0, 
      "time": 1492073409.0
    }, 
    {
      "pos": [
        37.32511279, 
        -122.04565925, 
        51.0
      ], 
      "rt": 53.0, 
      "time": 1492073410.0
    }, 
    {
      "pos": [
        37.32511985, 
        -122.04567291, 
        52.0
      ], 
      "rt": 54.0, 
      "time": 1492073411.0
    }, 
    {
      "pos": [
        37.32512803, 
        -122.04568468, 
        51.0
      ], 
      "rt": 55.0, 
      "time": 1492073412.0
    }, 
    {
      "pos": [
        37.32513671, 
        -122.04569361, 
        51.0
      ], 
      "rt": 56.0, 
      "time": 1492073413.0
    }, 
    {
      "pos": [
        37.32514569, 
        -122.0457, 
        51.0
      ], 
      "rt": 57.0, 
      "time": 1492073414.0
    }, 
    {
      "pos": [
        37.3251565, 
        -122.04570364, 
        50.0
      ], 
      "rt": 58.0, 
      "time": 1492073415.0
    }, 
    {
      "pos": [
        37.32516889, 
        -122.04570754, 
        51.0
      ], 
      "rt": 59.0, 
      "time": 1492073416.0
    }, 
    {
      "pos": [
        37.325183, 
        -122.04571035, 
        51.0
      ], 
      "rt": 60.0, 
      "time": 1492073417.0
    }, 
    {
      "pos": [
        37.32519661, 
        -122.04571221, 
        52.0
      ], 
      "rt": 61.0, 
      "time": 1492073418.0
    }, 
    {
      "pos": [
        37.32521211, 
        -122.04571408, 
        51.0
      ], 
      "rt": 62.0, 
      "time": 1492073419.0
    }, 
    {
      "pos": [
        37.32522999, 
        -122.04571546, 
        50.0
      ], 
      "rt": 63.0, 
      "time": 1492073420.0
    }, 
    {
      "pos": [
        37.32524904, 
        -122.04571854, 
        51.0
      ], 
      "rt": 64.0, 
      "time": 1492073421.0
    }, 
    {
      "pos": [
        37.32526547, 
        -122.04572175, 
        50.0
      ], 
      "rt": 65.0, 
      "time": 1492073422.0
    }, 
    {
      "pos": [
        37.32527998, 
        -122.04572433, 
        50.0
      ], 
      "rt": 66.0, 
      "time": 1492073423.0
    }, 
    {
      "pos": [
        37.32529158, 
        -122.0457262, 
        50.0
      ], 
      "rt": 67.0, 
      "time": 1492073424.0
    }, 
    {
      "pos": [
        37.32530222, 
        -122.04572686, 
        51.0
      ], 
      "rt": 68.0, 
      "time": 1492073425.0
    }, 
    {
      "pos": [
        37.32531311, 
        -122.04572798, 
        51.0
      ], 
      "rt": 69.0, 
      "time": 1492073426.0
    }, 
    {
      "pos": [
        37.32532479, 
        -122.04573071, 
        51.0
      ], 
      "rt": 70.0, 
      "time": 1492073427.0
    }, 
    {
      "pos": [
        37.32533838, 
        -122.04573392, 
        51.0
      ], 
      "rt": 71.0, 
      "time": 1492073428.0
    }, 
    {
      "pos": [
        37.32535258, 
        -122.04573634, 
        51.0
      ], 
      "rt": 72.0, 
      "time": 1492073429.0
    }, 
    {
      "pos": [
        37.32536548, 
        -122.04573597, 
        51.0
      ], 
      "rt": 73.0, 
      "time": 1492073430.0
    }, 
    {
      "pos": [
        37.32538046, 
        -122.04573294, 
        51.0
      ], 
      "rt": 74.0, 
      "time": 1492073431.0
    }, 
    {
      "pos": [
        37.32539499, 
        -122.04572929, 
        51.0
      ], 
      "rt": 75.0, 
      "time": 1492073432.0
    }, 
    {
      "pos": [
        37.32540829, 
        -122.04572653, 
        50.0
      ], 
      "rt": 76.0, 
      "time": 1492073433.0
    }, 
    {
      "pos": [
        37.3254238, 
        -122.04572565, 
        50.0
      ], 
      "rt": 77.0, 
      "time": 1492073434.0
    }, 
    {
      "pos": [
        37.32544007, 
        -122.04572543, 
        50.0
      ], 
      "rt": 78.0, 
      "time": 1492073435.0
    }, 
    {
      "pos": [
        37.32545655, 
        -122.04572683, 
        50.0
      ], 
      "rt": 79.0, 
      "time": 1492073436.0
    }, 
    {
      "pos": [
        37.32547308, 
        -122.04573068, 
        50.0
      ], 
      "rt": 80.0, 
      "time": 1492073437.0
    }, 
    {
      "pos": [
        37.32548922, 
        -122.04573629, 
        50.0
      ], 
      "rt": 81.0, 
      "time": 1492073438.0
    }, 
    {
      "pos": [
        37.32550387, 
        -122.04574351, 
        51.0
      ], 
      "rt": 82.0, 
      "time": 1492073439.0
    }, 
    {
      "pos": [
        37.32551864, 
        -122.04575183, 
        51.0
      ], 
      "rt": 83.0, 
      "time": 1492073440.0
    }, 
    {
      "pos": [
        37.32553378, 
        -122.04576174, 
        51.0
      ], 
      "rt": 84.0, 
      "time": 1492073441.0
    }, 
    {
      "pos": [
        37.32554558, 
        -122.04577238, 
        52.0
      ], 
      "rt": 85.0, 
      "time": 1492073442.0
    }, 
    {
      "pos": [
        37.32555509, 
        -122.04578458, 
        52.0
      ], 
      "rt": 86.0, 
      "time": 1492073443.0
    }, 
    {
      "pos": [
        37.32556291, 
        -122.04579674, 
        52.0
      ], 
      "rt": 87.0, 
      "time": 1492073444.0
    }, 
    {
      "pos": [
        37.32556991, 
        -122.04580858, 
        52.0
      ], 
      "rt": 88.0, 
      "time": 1492073445.0
    }, 
    {
      "pos": [
        37.32557608, 
        -122.04582196, 
        52.0
      ], 
      "rt": 89.0, 
      "time": 1492073446.0
    }, 
    {
      "pos": [
        37.32557854, 
        -122.04583088, 
        51.0
      ], 
      "rt": 90.0, 
      "time": 1492073447.0
    }, 
    {
      "pos": [
        37.32557995, 
        -122.04584058, 
        50.0
      ], 
      "rt": 91.0, 
      "time": 1492073448.0
    }, 
    {
      "pos": [
        37.32558189, 
        -122.04585293, 
        51.0
      ], 
      "rt": 92.0, 
      "time": 1492073449.0
    }, 
    {
      "pos": [
        37.32558119, 
        -122.04586186, 
        50.0
      ], 
      "rt": 93.0, 
      "time": 1492073450.0
    }, 
    {
      "pos": [
        37.32558102, 
        -122.04586766, 
        51.0
      ], 
      "rt": 94.0, 
      "time": 1492073451.0
    }, 
    {
      "pos": [
        37.32558278, 
        -122.04587393, 
        50.0
      ], 
      "rt": 95.0, 
      "time": 1492073452.0
    }, 
    {
      "pos": [
        37.32558554, 
        -122.04587924, 
        50.0
      ], 
      "rt": 96.0, 
      "time": 1492073453.0
    }, 
    {
      "pos": [
        37.32558841, 
        -122.04588351, 
        50.0
      ], 
      "rt": 97.0, 
      "time": 1492073454.0
    }, 
    {
      "pos": [
        37.32559309, 
        -122.04588682, 
        50.0
      ], 
      "rt": 98.0, 
      "time": 1492073455.0
    }, 
    {
      "pos": [
        37.32560016, 
        -122.04589051, 
        49.0
      ], 
      "rt": 99.0, 
      "time": 1492073456.0
    }, 
    {
      "pos": [
        37.32560879, 
        -122.0458933, 
        48.0
      ], 
      "rt": 100.0, 
      "time": 1492073457.0
    }, 
    {
      "pos": [
        37.32561906, 
        -122.045894, 
        47.0
      ], 
      "rt": 101.0, 
      "time": 1492073458.0
    }, 
    {
      "pos": [
        37.32562944, 
        -122.045895, 
        47.0
      ], 
      "rt": 102.0, 
      "time": 1492073459.0
    }, 
    {
      "pos": [
        37.32564232, 
        -122.04589582, 
        47.0
      ], 
      "rt": 103.0, 
      "time": 1492073460.0
    }, 
    {
      "pos": [
        37.3256572, 
        -122.04589417, 
        46.0
      ], 
      "rt": 104.0, 
      "time": 1492073461.0
    }, 
    {
      "pos": [
        37.3256733, 
        -122.04589081, 
        47.0
      ], 
      "rt": 105.0, 
      "time": 1492073462.0
    }, 
    {
      "pos": [
        37.3256901, 
        -122.04588746, 
        47.0
      ], 
      "rt": 106.0, 
      "time": 1492073463.0
    }, 
    {
      "pos": [
        37.32570645, 
        -122.04588536, 
        47.0
      ], 
      "rt": 107.0, 
      "time": 1492073464.0
    }, 
    {
      "pos": [
        37.32572345, 
        -122.04588493, 
        46.0
      ], 
      "rt": 108.0, 
      "time": 1492073465.0
    }, 
    {
      "pos": [
        37.32574053, 
        -122.04588517, 
        46.0
      ], 
      "rt": 109.0, 
      "time": 1492073466.0
    }, 
    {
      "pos": [
        37.32575662, 
        -122.04588591, 
        46.0
      ], 
      "rt": 110.0, 
      "time": 1492073467.0
    }, 
    {
      "pos": [
        37.32577384, 
        -122.04588688, 
        46.0
      ], 
      "rt": 111.0, 
      "time": 1492073468.0
    }, 
    {
      "pos": [
        37.32579419, 
        -122.04588868, 
        46.0
      ], 
      "rt": 112.0, 
      "time": 1492073469.0
    }, 
    {
      "pos": [
        37.32581164, 
        -122.04589073, 
        46.0
      ], 
      "rt": 113.0, 
      "time": 1492073470.0
    }, 
    {
      "pos": [
        37.32583106, 
        -122.04589278, 
        46.0
      ], 
      "rt": 114.0, 
      "time": 1492073471.0
    }, 
    {
      "pos": [
        37.32584469, 
        -122.04589284, 
        48.0
      ], 
      "rt": 115.0, 
      "time": 1492073472.0
    }, 
    {
      "pos": [
        37.32586022, 
        -122.04589215, 
        47.0
      ], 
      "rt": 116.0, 
      "time": 1492073473.0
    }, 
    {
      "pos": [
        37.32587867, 
        -122.04589017, 
        46.0
      ], 
      "rt": 117.0, 
      "time": 1492073474.0
    }, 
    {
      "pos": [
        37.32589692, 
        -122.04588776, 
        47.0
      ], 
      "rt": 118.0, 
      "time": 1492073475.0
    }, 
    {
      "pos": [
        37.32591265, 
        -122.04588314, 
        48.0
      ], 
      "rt": 119.0, 
      "time": 1492073476.0
    }, 
    {
      "pos": [
        37.32592654, 
        -122.04587851, 
        47.0
      ], 
      "rt": 120.0, 
      "time": 1492073477.0
    }, 
    {
      "pos": [
        37.32594366, 
        -122.04587347, 
        46.0
      ], 
      "rt": 121.0, 
      "time": 1492073478.0
    }, 
    {
      "pos": [
        37.3259601, 
        -122.04586774, 
        45.0
      ], 
      "rt": 122.0, 
      "time": 1492073479.0
    }, 
    {
      "pos": [
        37.32597642, 
        -122.04586155, 
        43.0
      ], 
      "rt": 123.0, 
      "time": 1492073480.0
    }, 
    {
      "pos": [
        37.32598905, 
        -122.04585352, 
        43.0
      ], 
      "rt": 124.0, 
      "time": 1492073481.0
    }, 
    {
      "pos": [
        37.32600272, 
        -122.0458454, 
        44.0
      ], 
      "rt": 125.0, 
      "time": 1492073482.0
    }, 
    {
      "pos": [
        37.32601526, 
        -122.04583934, 
        44.0
      ], 
      "rt": 126.0, 
      "time": 1492073483.0
    }, 
    {
      "pos": [
        37.32602863, 
        -122.04583548, 
        44.0
      ], 
      "rt": 127.0, 
      "time": 1492073484.0
    }, 
    {
      "pos": [
        37.32604433, 
        -122.04583073, 
        44.0
      ], 
      "rt": 128.0, 
      "time": 1492073485.0
    }, 
    {
      "pos": [
        37.326062, 
        -122.04582085, 
        45.0
      ], 
      "rt": 129.0, 
      "time": 1492073486.0
    }, 
    {
      "pos": [
        37.3260805, 
        -122.04580843, 
        45.0
      ], 
      "rt": 130.0, 
      "time": 1492073487.0
    }, 
    {
      "pos": [
        37.32609952, 
        -122.04579441, 
        46.0
      ], 
      "rt": 131.0, 
      "time": 1492073488.0
    }, 
    {
      "pos": [
        37.32611895, 
        -122.0457805, 
        46.0
      ], 
      "rt": 132.0, 
      "time": 1492073489.0
    }, 
    {
      "pos": [
        37.32613483, 
        -122.0457663, 
        45.0
      ], 
      "rt": 133.0, 
      "time": 1492073490.0
    }, 
    {
      "pos": [
        37.3261447, 
        -122.04575471, 
        43.0
      ], 
      "rt": 134.0, 
      "time": 1492073491.0
    }, 
    {
      "pos": [
        37.32615661, 
        -122.04574315, 
        43.0
      ], 
      "rt": 135.0, 
      "time": 1492073492.0
    }, 
    {
      "pos": [
        37.32617026, 
        -122.04573388, 
        43.0
      ], 
      "rt": 136.0, 
      "time": 1492073493.0
    }, 
    {
      "pos": [
        37.32618565, 
        -122.04572673, 
        43.0
      ], 
      "rt": 137.0, 
      "time": 1492073494.0
    }, 
    {
      "pos": [
        37.32620217, 
        -122.04571988, 
        43.0
      ], 
      "rt": 138.0, 
      "time": 1492073495.0
    }, 
    {
      "pos": [
        37.32621784, 
        -122.04571022, 
        43.0
      ], 
      "rt": 139.0, 
      "time": 1492073496.0
    }, 
    {
      "pos": [
        37.32623177, 
        -122.04570052, 
        43.0
      ], 
      "rt": 140.0, 
      "time": 1492073497.0
    }, 
    {
      "pos": [
        37.32624699, 
        -122.04569209, 
        44.0
      ], 
      "rt": 141.0, 
      "time": 1492073498.0
    }, 
    {
      "pos": [
        37.32626542, 
        -122.04568544, 
        44.0
      ], 
      "rt": 142.0, 
      "time": 1492073499.0
    }, 
    {
      "pos": [
        37.32628404, 
        -122.04568061, 
        43.0
      ], 
      "rt": 143.0, 
      "time": 1492073500.0
    }, 
    {
      "pos": [
        37.32630804, 
        -122.04568117, 
        43.0
      ], 
      "rt": 144.0, 
      "time": 1492073501.0
    }, 
    {
      "pos": [
        37.32633065, 
        -122.04568145, 
        45.0
      ], 
      "rt": 145.0, 
      "time": 1492073502.0
    }, 
    {
      "pos": [
        37.32635166, 
        -122.04568074, 
        45.0
      ], 
      "rt": 146.0, 
      "time": 1492073503.0
    }, 
    {
      "pos": [
        37.32637208, 
        -122.04568503, 
        43.0
      ], 
      "rt": 147.0, 
      "time": 1492073504.0
    }, 
    {
      "pos": [
        37.32639061, 
        -122.04569022, 
        41.0
      ], 
      "rt": 148.0, 
      "time": 1492073505.0
    }, 
    {
      "pos": [
        37.326408, 
        -122.04569642, 
        41.0
      ], 
      "rt": 149.0, 
      "time": 1492073506.0
    }, 
    {
      "pos": [
        37.32642668, 
        -122.04570348, 
        42.0
      ], 
      "rt": 150.0, 
      "time": 1492073507.0
    }, 
    {
      "pos": [
        37.32644776, 
        -122.04570924, 
        42.0
      ], 
      "rt": 151.0, 
      "time": 1492073508.0
    }, 
    {
      "pos": [
        37.32646683, 
        -122.04571004, 
        42.0
      ], 
      "rt": 152.0, 
      "time": 1492073509.0
    }, 
    {
      "pos": [
        37.32648233, 
        -122.04570601, 
        41.0
      ], 
      "rt": 153.0, 
      "time": 1492073510.0
    }, 
    {
      "pos": [
        37.32649527, 
        -122.04569474, 
        42.0
      ], 
      "rt": 154.0, 
      "time": 1492073511.0
    }, 
    {
      "pos": [
        37.32650488, 
        -122.04567889, 
        43.0
      ], 
      "rt": 155.0, 
      "time": 1492073512.0
    }, 
    {
      "pos": [
        37.32651508, 
        -122.04566686, 
        41.0
      ], 
      "rt": 156.0, 
      "time": 1492073513.0
    }, 
    {
      "pos": [
        37.32652221, 
        -122.0456525, 
        41.0
      ], 
      "rt": 157.0, 
      "time": 1492073514.0
    }, 
    {
      "pos": [
        37.32653267, 
        -122.04563908, 
        40.0
      ], 
      "rt": 158.0, 
      "time": 1492073515.0
    }, 
    {
      "pos": [
        37.32654289, 
        -122.04562347, 
        41.0
      ], 
      "rt": 159.0, 
      "time": 1492073516.0
    }, 
    {
      "pos": [
        37.32655115, 
        -122.04560872, 
        41.0
      ], 
      "rt": 160.0, 
      "time": 1492073517.0
    }, 
    {
      "pos": [
        37.32655992, 
        -122.04559563, 
        42.0
      ], 
      "rt": 161.0, 
      "time": 1492073518.0
    }, 
    {
      "pos": [
        37.3265662, 
        -122.04558195, 
        42.0
      ], 
      "rt": 162.0, 
      "time": 1492073519.0
    }, 
    {
      "pos": [
        37.32657022, 
        -122.0455662, 
        42.0
      ], 
      "rt": 163.0, 
      "time": 1492073520.0
    }, 
    {
      "pos": [
        37.32657068, 
        -122.04554995, 
        41.0
      ], 
      "rt": 164.0, 
      "time": 1492073521.0
    }, 
    {
      "pos": [
        37.32657099, 
        -122.04553909, 
        41.0
      ], 
      "rt": 165.0, 
      "time": 1492073522.0
    }, 
    {
      "pos": [
        37.32656883, 
        -122.04553202, 
        40.0
      ], 
      "rt": 166.0, 
      "time": 1492073523.0
    }, 
    {
      "pos": [
        37.32656242, 
        -122.04552431, 
        40.0
      ], 
      "rt": 167.0, 
      "time": 1492073524.0
    }, 
    {
      "pos": [
        37.32655417, 
        -122.04551971, 
        40.0
      ], 
      "rt": 168.0, 
      "time": 1492073525.0
    }, 
    {
      "pos": [
        37.32654352, 
        -122.04551245, 
        41.0
      ], 
      "rt": 169.0, 
      "time": 1492073526.0
    }, 
    {
      "pos": [
        37.32652953, 
        -122.04550785, 
        43.0
      ], 
      "rt": 170.0, 
      "time": 1492073527.0
    }, 
    {
      "pos": [
        37.32651394, 
        -122.04550616, 
        44.0
      ], 
      "rt": 171.0, 
      "time": 1492073528.0
    }, 
    {
      "pos": [
        37.3264949, 
        -122.04550593, 
        45.0
      ], 
      "rt": 172.0, 
      "time": 1492073529.0
    }, 
    {
      "pos": [
        37.32647942, 
        -122.04550567, 
        46.0
      ], 
      "rt": 173.0, 
      "time": 1492073530.0
    }, 
    {
      "pos": [
        37.32646468, 
        -122.04550716, 
        47.0
      ], 
      "rt": 174.0, 
      "time": 1492073531.0
    }, 
    {
      "pos": [
        37.32645029, 
        -122.04551118, 
        46.0
      ], 
      "rt": 175.0, 
      "time": 1492073532.0
    }, 
    {
      "pos": [
        37.32639762, 
        -122.04552218, 
        49.0
      ], 
      "rt": 178.0, 
      "time": 1492073535.0
    }, 
    {
      "pos": [
        37.32638194, 
        -122.04552461, 
        49.0
      ], 
      "rt": 179.0, 
      "time": 1492073536.0
    }, 
    {
      "pos": [
        37.32636703, 
        -122.04552692, 
        50.0
      ], 
      "rt": 180.0, 
      "time": 1492073537.0
    }, 
    {
      "pos": [
        37.32635103, 
        -122.04553002, 
        50.0
      ], 
      "rt": 181.0, 
      "time": 1492073538.0
    }, 
    {
      "pos": [
        37.32633344, 
        -122.04553139, 
        50.0
      ], 
      "rt": 182.0, 
      "time": 1492073539.0
    }, 
    {
      "pos": [
        37.32631878, 
        -122.04553647, 
        50.0
      ], 
      "rt": 183.0, 
      "time": 1492073540.0
    }, 
    {
      "pos": [
        37.32630796, 
        -122.0455413, 
        50.0
      ], 
      "rt": 184.0, 
      "time": 1492073541.0
    }, 
    {
      "pos": [
        37.32630097, 
        -122.04554922, 
        50.0
      ], 
      "rt": 185.0, 
      "time": 1492073542.0
    }, 
    {
      "pos": [
        37.32629335, 
        -122.0455574, 
        49.0
      ], 
      "rt": 186.0, 
      "time": 1492073543.0
    }, 
    {
      "pos": [
        37.32628712, 
        -122.04556742, 
        50.0
      ], 
      "rt": 187.0, 
      "time": 1492073544.0
    }, 
    {
      "pos": [
        37.32627837, 
        -122.04557461, 
        51.0
      ], 
      "rt": 188.0, 
      "time": 1492073545.0
    }, 
    {
      "pos": [
        37.32626587, 
        -122.04557758, 
        50.0
      ], 
      "rt": 189.0, 
      "time": 1492073546.0
    }, 
    {
      "pos": [
        37.32624966, 
        -122.04557466, 
        51.0
      ], 
      "rt": 190.0, 
      "time": 1492073547.0
    }, 
    {
      "pos": [
        37.32623434, 
        -122.04556916, 
        52.0
      ], 
      "rt": 191.0, 
      "time": 1492073548.0
    }, 
    {
      "pos": [
        37.32622199, 
        -122.04556045, 
        51.0
      ], 
      "rt": 192.0, 
      "time": 1492073549.0
    }, 
    {
      "pos": [
        37.32621028, 
        -122.04554777, 
        51.0
      ], 
      "rt": 193.0, 
      "time": 1492073550.0
    }, 
    {
      "pos": [
        37.32620089, 
        -122.04553257, 
        51.0
      ], 
      "rt": 194.0, 
      "time": 1492073551.0
    }, 
    {
      "pos": [
        37.32619225, 
        -122.04551455, 
        51.0
      ], 
      "rt": 195.0, 
      "time": 1492073552.0
    }, 
    {
      "pos": [
        37.32618486, 
        -122.04549667, 
        51.0
      ], 
      "rt": 196.0, 
      "time": 1492073553.0
    }, 
    {
      "pos": [
        37.32617747, 
        -122.04547616, 
        51.0
      ], 
      "rt": 197.0, 
      "time": 1492073554.0
    }, 
    {
      "pos": [
        37.32617057, 
        -122.04545275, 
        51.0
      ], 
      "rt": 198.0, 
      "time": 1492073555.0
    }, 
    {
      "pos": [
        37.32616417, 
        -122.045427, 
        51.0
      ], 
      "rt": 199.0, 
      "time": 1492073556.0
    }, 
    {
      "pos": [
        37.32615846, 
        -122.04540054, 
        51.0
      ], 
      "rt": 200.0, 
      "time": 1492073557.0
    }, 
    {
      "pos": [
        37.32615394, 
        -122.04537389, 
        51.0
      ], 
      "rt": 201.0, 
      "time": 1492073558.0
    }, 
    {
      "pos": [
        37.32614992, 
        -122.04535156, 
        51.0
      ], 
      "rt": 202.0, 
      "time": 1492073559.0
    }, 
    {
      "pos": [
        37.32614703, 
        -122.04533857, 
        49.0
      ], 
      "rt": 203.0, 
      "time": 1492073560.0
    }, 
    {
      "pos": [
        37.32614477, 
        -122.0453234, 
        50.0
      ], 
      "rt": 204.0, 
      "time": 1492073561.0
    }, 
    {
      "pos": [
        37.32614233, 
        -122.04530841, 
        49.0
      ], 
      "rt": 205.0, 
      "time": 1492073562.0
    }, 
    {
      "pos": [
        37.32613969, 
        -122.04529249, 
        50.0
      ], 
      "rt": 206.0, 
      "time": 1492073563.0
    }, 
    {
      "pos": [
        37.32613729, 
        -122.04527536, 
        48.0
      ], 
      "rt": 207.0, 
      "time": 1492073564.0
    }, 
    {
      "pos": [
        37.32613594, 
        -122.04526137, 
        47.0
      ], 
      "rt": 208.0, 
      "time": 1492073565.0
    }, 
    {
      "pos": [
        37.32613492, 
        -122.04524573, 
        47.0
      ], 
      "rt": 209.0, 
      "time": 1492073566.0
    }, 
    {
      "pos": [
        37.32613352, 
        -122.04522583, 
        47.0
      ], 
      "rt": 210.0, 
      "time": 1492073567.0
    }, 
    {
      "pos": [
        37.32613182, 
        -122.04520321, 
        48.0
      ], 
      "rt": 211.0, 
      "time": 1492073568.0
    }, 
    {
      "pos": [
        37.32613057, 
        -122.04518261, 
        47.0
      ], 
      "rt": 212.0, 
      "time": 1492073569.0
    }, 
    {
      "pos": [
        37.32612903, 
        -122.04516408, 
        47.0
      ], 
      "rt": 213.0, 
      "time": 1492073570.0
    }, 
    {
      "pos": [
        37.32612768, 
        -122.04514594, 
        45.0
      ], 
      "rt": 214.0, 
      "time": 1492073571.0
    }, 
    {
      "pos": [
        37.32612706, 
        -122.04513026, 
        44.0
      ], 
      "rt": 215.0, 
      "time": 1492073572.0
    }, 
    {
      "pos": [
        37.32613189, 
        -122.04511251, 
        45.0
      ], 
      "rt": 216.0, 
      "time": 1492073573.0
    }, 
    {
      "pos": [
        37.32613573, 
        -122.04509649, 
        44.0
      ], 
      "rt": 217.0, 
      "time": 1492073574.0
    }, 
    {
      "pos": [
        37.32613824, 
        -122.04507619, 
        45.0
      ], 
      "rt": 218.0, 
      "time": 1492073575.0
    }, 
    {
      "pos": [
        37.32614007, 
        -122.04505174, 
        47.0
      ], 
      "rt": 219.0, 
      "time": 1492073576.0
    }, 
    {
      "pos": [
        37.32614272, 
        -122.04502908, 
        48.0
      ], 
      "rt": 220.0, 
      "time": 1492073577.0
    }, 
    {
      "pos": [
        37.32614514, 
        -122.04500508, 
        47.0
      ], 
      "rt": 221.0, 
      "time": 1492073578.0
    }, 
    {
      "pos": [
        37.32614669, 
        -122.04498312, 
        47.0
      ], 
      "rt": 222.0, 
      "time": 1492073579.0
    }, 
    {
      "pos": [
        37.32614731, 
        -122.04496203, 
        47.0
      ], 
      "rt": 223.0, 
      "time": 1492073580.0
    }, 
    {
      "pos": [
        37.3261479, 
        -122.04494058, 
        47.0
      ], 
      "rt": 224.0, 
      "time": 1492073581.0
    }, 
    {
      "pos": [
        37.32614781, 
        -122.04491898, 
        47.0
      ], 
      "rt": 225.0, 
      "time": 1492073582.0
    }, 
    {
      "pos": [
        37.3261469, 
        -122.04489825, 
        46.0
      ], 
      "rt": 226.0, 
      "time": 1492073583.0
    }, 
    {
      "pos": [
        37.32614528, 
        -122.04487724, 
        47.0
      ], 
      "rt": 227.0, 
      "time": 1492073584.0
    }, 
    {
      "pos": [
        37.32614434, 
        -122.0448603, 
        46.0
      ], 
      "rt": 228.0, 
      "time": 1492073585.0
    }, 
    {
      "pos": [
        37.32614439, 
        -122.04484165, 
        46.0
      ], 
      "rt": 229.0, 
      "time": 1492073586.0
    }, 
    {
      "pos": [
        37.32614557, 
        -122.04482396, 
        46.0
      ], 
      "rt": 230.0, 
      "time": 1492073587.0
    }, 
    {
      "pos": [
        37.32614712, 
        -122.044807, 
        45.0
      ], 
      "rt": 231.0, 
      "time": 1492073588.0
    }, 
    {
      "pos": [
        37.32614884, 
        -122.04479136, 
        44.0
      ], 
      "rt": 232.0, 
      "time": 1492073589.0
    }, 
    {
      "pos": [
        37.32615043, 
        -122.04477559, 
        44.0
      ], 
      "rt": 233.0, 
      "time": 1492073590.0
    }, 
    {
      "pos": [
        37.32615237, 
        -122.04475809, 
        44.0
      ], 
      "rt": 234.0, 
      "time": 1492073591.0
    }, 
    {
      "pos": [
        37.32615502, 
        -122.0447401, 
        43.0
      ], 
      "rt": 235.0, 
      "time": 1492073592.0
    }, 
    {
      "pos": [
        37.32615725, 
        -122.04472527, 
        42.0
      ], 
      "rt": 236.0, 
      "time": 1492073593.0
    }, 
    {
      "pos": [
        37.32615857, 
        -122.04470868, 
        42.0
      ], 
      "rt": 237.0, 
      "time": 1492073594.0
    }, 
    {
      "pos": [
        37.32615552, 
        -122.04469208, 
        42.0
      ], 
      "rt": 238.0, 
      "time": 1492073595.0
    }, 
    {
      "pos": [
        37.32615069, 
        -122.04467499, 
        42.0
      ], 
      "rt": 239.0, 
      "time": 1492073596.0
    }, 
    {
      "pos": [
        37.32614522, 
        -122.04465917, 
        43.0
      ], 
      "rt": 240.0, 
      "time": 1492073597.0
    }, 
    {
      "pos": [
        37.32613699, 
        -122.04464479, 
        44.0
      ], 
      "rt": 241.0, 
      "time": 1492073598.0
    }, 
    {
      "pos": [
        37.32612667, 
        -122.04462776, 
        48.0
      ], 
      "rt": 242.0, 
      "time": 1492073599.0
    }, 
    {
      "pos": [
        37.32611548, 
        -122.04461353, 
        48.0
      ], 
      "rt": 243.0, 
      "time": 1492073600.0
    }, 
    {
      "pos": [
        37.32610409, 
        -122.04460082, 
        48.0
      ], 
      "rt": 244.0, 
      "time": 1492073601.0
    }, 
    {
      "pos": [
        37.32609146, 
        -122.04458889, 
        50.0
      ], 
      "rt": 245.0, 
      "time": 1492073602.0
    }, 
    {
      "pos": [
        37.32607734, 
        -122.04457781, 
        50.0
      ], 
      "rt": 246.0, 
      "time": 1492073603.0
    }, 
    {
      "pos": [
        37.32606356, 
        -122.04456921, 
        51.0
      ], 
      "rt": 247.0, 
      "time": 1492073604.0
    }, 
    {
      "pos": [
        37.32604989, 
        -122.04456158, 
        50.0
      ], 
      "rt": 248.0, 
      "time": 1492073605.0
    }, 
    {
      "pos": [
        37.32603606, 
        -122.04455491, 
        49.0
      ], 
      "rt": 249.0, 
      "time": 1492073606.0
    }, 
    {
      "pos": [
        37.32602167, 
        -122.0445465, 
        50.0
      ], 
      "rt": 250.0, 
      "time": 1492073607.0
    }, 
    {
      "pos": [
        37.32600781, 
        -122.04453781, 
        50.0
      ], 
      "rt": 251.0, 
      "time": 1492073608.0
    }, 
    {
      "pos": [
        37.3259927, 
        -122.04452689, 
        50.0
      ], 
      "rt": 252.0, 
      "time": 1492073609.0
    }, 
    {
      "pos": [
        37.32597865, 
        -122.04451548, 
        49.0
      ], 
      "rt": 253.0, 
      "time": 1492073610.0
    }, 
    {
      "pos": [
        37.32596619, 
        -122.04450393, 
        49.0
      ], 
      "rt": 254.0, 
      "time": 1492073611.0
    }, 
    {
      "pos": [
        37.32595563, 
        -122.04449374, 
        49.0
      ], 
      "rt": 255.0, 
      "time": 1492073612.0
    }, 
    {
      "pos": [
        37.32594721, 
        -122.0444829, 
        49.0
      ], 
      "rt": 256.0, 
      "time": 1492073613.0
    }, 
    {
      "pos": [
        37.32594271, 
        -122.04446836, 
        49.0
      ], 
      "rt": 257.0, 
      "time": 1492073614.0
    }, 
    {
      "pos": [
        37.32594505, 
        -122.04444979, 
        49.0
      ], 
      "rt": 258.0, 
      "time": 1492073615.0
    }, 
    {
      "pos": [
        37.32595331, 
        -122.04443176, 
        49.0
      ], 
      "rt": 259.0, 
      "time": 1492073616.0
    }, 
    {
      "pos": [
        37.32596399, 
        -122.04441537, 
        49.0
      ], 
      "rt": 260.0, 
      "time": 1492073617.0
    }, 
    {
      "pos": [
        37.32597619, 
        -122.04440063, 
        49.0
      ], 
      "rt": 261.0, 
      "time": 1492073618.0
    }, 
    {
      "pos": [
        37.32598933, 
        -122.04438409, 
        49.0
      ], 
      "rt": 262.0, 
      "time": 1492073619.0
    }, 
    {
      "pos": [
        37.32600186, 
        -122.04436656, 
        49.0
      ], 
      "rt": 263.0, 
      "time": 1492073620.0
    }, 
    {
      "pos": [
        37.32601234, 
        -122.04434827, 
        48.0
      ], 
      "rt": 264.0, 
      "time": 1492073621.0
    }, 
    {
      "pos": [
        37.32602073, 
        -122.04432948, 
        49.0
      ], 
      "rt": 265.0, 
      "time": 1492073622.0
    }, 
    {
      "pos": [
        37.32602793, 
        -122.0443092, 
        50.0
      ], 
      "rt": 266.0, 
      "time": 1492073623.0
    }, 
    {
      "pos": [
        37.32603462, 
        -122.04428822, 
        49.0
      ], 
      "rt": 267.0, 
      "time": 1492073624.0
    }, 
    {
      "pos": [
        37.32604089, 
        -122.04426745, 
        49.0
      ], 
      "rt": 268.0, 
      "time": 1492073625.0
    }, 
    {
      "pos": [
        37.32604758, 
        -122.0442465, 
        49.0
      ], 
      "rt": 269.0, 
      "time": 1492073626.0
    }, 
    {
      "pos": [
        37.32605385, 
        -122.04422516, 
        49.0
      ], 
      "rt": 270.0, 
      "time": 1492073627.0
    }, 
    {
      "pos": [
        37.32606021, 
        -122.0442034, 
        49.0
      ], 
      "rt": 271.0, 
      "time": 1492073628.0
    }, 
    {
      "pos": [
        37.32606706, 
        -122.0441832, 
        49.0
      ], 
      "rt": 272.0, 
      "time": 1492073629.0
    }, 
    {
      "pos": [
        37.32607531, 
        -122.04416502, 
        49.0
      ], 
      "rt": 273.0, 
      "time": 1492073630.0
    }, 
    {
      "pos": [
        37.32608458, 
        -122.044147, 
        49.0
      ], 
      "rt": 274.0, 
      "time": 1492073631.0
    }, 
    {
      "pos": [
        37.32609445, 
        -122.04412942, 
        49.0
      ], 
      "rt": 275.0, 
      "time": 1492073632.0
    }, 
    {
      "pos": [
        37.32610456, 
        -122.04411232, 
        50.0
      ], 
      "rt": 276.0, 
      "time": 1492073633.0
    }, 
    {
      "pos": [
        37.32611479, 
        -122.04409635, 
        49.0
      ], 
      "rt": 277.0, 
      "time": 1492073634.0
    }, 
    {
      "pos": [
        37.32612386, 
        -122.04408051, 
        49.0
      ], 
      "rt": 278.0, 
      "time": 1492073635.0
    }, 
    {
      "pos": [
        37.32613113, 
        -122.0440629, 
        49.0
      ], 
      "rt": 279.0, 
      "time": 1492073636.0
    }, 
    {
      "pos": [
        37.32613644, 
        -122.04404473, 
        49.0
      ], 
      "rt": 280.0, 
      "time": 1492073637.0
    }, 
    {
      "pos": [
        37.32613923, 
        -122.04403436, 
        48.0
      ], 
      "rt": 281.0, 
      "time": 1492073638.0
    }, 
    {
      "pos": [
        37.32613938, 
        -122.04402331, 
        48.0
      ], 
      "rt": 282.0, 
      "time": 1492073639.0
    }, 
    {
      "pos": [
        37.32613927, 
        -122.04400533, 
        48.0
      ], 
      "rt": 283.0, 
      "time": 1492073640.0
    }, 
    {
      "pos": [
        37.32613792, 
        -122.04398679, 
        47.0
      ], 
      "rt": 284.0, 
      "time": 1492073641.0
    }, 
    {
      "pos": [
        37.32613726, 
        -122.04396931, 
        47.0
      ], 
      "rt": 285.0, 
      "time": 1492073642.0
    }, 
    {
      "pos": [
        37.3261372, 
        -122.04394853, 
        47.0
      ], 
      "rt": 286.0, 
      "time": 1492073643.0
    }, 
    {
      "pos": [
        37.32613461, 
        -122.0439298, 
        47.0
      ], 
      "rt": 287.0, 
      "time": 1492073644.0
    }, 
    {
      "pos": [
        37.32613072, 
        -122.04391356, 
        47.0
      ], 
      "rt": 288.0, 
      "time": 1492073645.0
    }, 
    {
      "pos": [
        37.3261273, 
        -122.04389547, 
        46.0
      ], 
      "rt": 289.0, 
      "time": 1492073646.0
    }, 
    {
      "pos": [
        37.32612498, 
        -122.04387671, 
        46.0
      ], 
      "rt": 290.0, 
      "time": 1492073647.0
    }, 
    {
      "pos": [
        37.32612345, 
        -122.04385763, 
        45.0
      ], 
      "rt": 291.0, 
      "time": 1492073648.0
    }, 
    {
      "pos": [
        37.32612201, 
        -122.04383827, 
        45.0
      ], 
      "rt": 292.0, 
      "time": 1492073649.0
    }, 
    {
      "pos": [
        37.32612147, 
        -122.04382003, 
        45.0
      ], 
      "rt": 293.0, 
      "time": 1492073650.0
    }, 
    {
      "pos": [
        37.32612079, 
        -122.04380107, 
        45.0
      ], 
      "rt": 294.0, 
      "time": 1492073651.0
    }, 
    {
      "pos": [
        37.32612037, 
        -122.04378193, 
        45.0
      ], 
      "rt": 295.0, 
      "time": 1492073652.0
    }, 
    {
      "pos": [
        37.32612049, 
        -122.04376334, 
        44.0
      ], 
      "rt": 296.0, 
      "time": 1492073653.0
    }, 
    {
      "pos": [
        37.32612102, 
        -122.04374289, 
        44.0
      ], 
      "rt": 297.0, 
      "time": 1492073654.0
    }, 
    {
      "pos": [
        37.32612205, 
        -122.04372048, 
        45.0
      ], 
      "rt": 298.0, 
      "time": 1492073655.0
    }, 
    {
      "pos": [
        37.3261232, 
        -122.04369885, 
        45.0
      ], 
      "rt": 299.0, 
      "time": 1492073656.0
    }, 
    {
      "pos": [
        37.3261237, 
        -122.04367672, 
        44.0
      ], 
      "rt": 300.0, 
      "time": 1492073657.0
    }, 
    {
      "pos": [
        37.32612506, 
        -122.04365476, 
        44.0
      ], 
      "rt": 301.0, 
      "time": 1492073658.0
    }, 
    {
      "pos": [
        37.32612665, 
        -122.04363319, 
        44.0
      ], 
      "rt": 302.0, 
      "time": 1492073659.0
    }, 
    {
      "pos": [
        37.32612923, 
        -122.04361259, 
        44.0
      ], 
      "rt": 303.0, 
      "time": 1492073660.0
    }, 
    {
      "pos": [
        37.3261311, 
        -122.04359077, 
        43.0
      ], 
      "rt": 304.0, 
      "time": 1492073661.0
    }, 
    {
      "pos": [
        37.32613292, 
        -122.04356877, 
        43.0
      ], 
      "rt": 305.0, 
      "time": 1492073662.0
    }, 
    {
      "pos": [
        37.32613309, 
        -122.04354908, 
        43.0
      ], 
      "rt": 306.0, 
      "time": 1492073663.0
    }, 
    {
      "pos": [
        37.32613301, 
        -122.04353339, 
        42.0
      ], 
      "rt": 307.0, 
      "time": 1492073664.0
    }, 
    {
      "pos": [
        37.32613398, 
        -122.04351631, 
        42.0
      ], 
      "rt": 308.0, 
      "time": 1492073665.0
    }, 
    {
      "pos": [
        37.3261345, 
        -122.0434986, 
        40.0
      ], 
      "rt": 309.0, 
      "time": 1492073666.0
    }, 
    {
      "pos": [
        37.3261348, 
        -122.0434814, 
        40.0
      ], 
      "rt": 310.0, 
      "time": 1492073667.0
    }, 
    {
      "pos": [
        37.32613679, 
        -122.04346297, 
        38.0
      ], 
      "rt": 311.0, 
      "time": 1492073668.0
    }, 
    {
      "pos": [
        37.32613772, 
        -122.04344831, 
        38.0
      ], 
      "rt": 312.0, 
      "time": 1492073669.0
    }, 
    {
      "pos": [
        37.32613982, 
        -122.04343147, 
        38.0
      ], 
      "rt": 313.0, 
      "time": 1492073670.0
    }, 
    {
      "pos": [
        37.32614214, 
        -122.0434143, 
        39.0
      ], 
      "rt": 314.0, 
      "time": 1492073671.0
    }, 
    {
      "pos": [
        37.32614461, 
        -122.04339654, 
        39.0
      ], 
      "rt": 315.0, 
      "time": 1492073672.0
    }, 
    {
      "pos": [
        37.32614458, 
        -122.04337656, 
        39.0
      ], 
      "rt": 316.0, 
      "time": 1492073673.0
    }, 
    {
      "pos": [
        37.32614417, 
        -122.04335496, 
        39.0
      ], 
      "rt": 317.0, 
      "time": 1492073674.0
    }, 
    {
      "pos": [
        37.3261442, 
        -122.04332998, 
        40.0
      ], 
      "rt": 318.0, 
      "time": 1492073675.0
    }, 
    {
      "pos": [
        37.32614411, 
        -122.04330414, 
        40.0
      ], 
      "rt": 319.0, 
      "time": 1492073676.0
    }, 
    {
      "pos": [
        37.32614416, 
        -122.04327735, 
        40.0
      ], 
      "rt": 320.0, 
      "time": 1492073677.0
    }, 
    {
      "pos": [
        37.3261434, 
        -122.04325218, 
        40.0
      ], 
      "rt": 321.0, 
      "time": 1492073678.0
    }, 
    {
      "pos": [
        37.32614234, 
        -122.04322835, 
        40.0
      ], 
      "rt": 322.0, 
      "time": 1492073679.0
    }, 
    {
      "pos": [
        37.32614073, 
        -122.0432054, 
        40.0
      ], 
      "rt": 323.0, 
      "time": 1492073680.0
    }, 
    {
      "pos": [
        37.32613864, 
        -122.04318177, 
        40.0
      ], 
      "rt": 324.0, 
      "time": 1492073681.0
    }, 
    {
      "pos": [
        37.32613552, 
        -122.04315755, 
        40.0
      ], 
      "rt": 325.0, 
      "time": 1492073682.0
    }, 
    {
      "pos": [
        37.3261307, 
        -122.04313559, 
        40.0
      ], 
      "rt": 326.0, 
      "time": 1492073683.0
    }, 
    {
      "pos": [
        37.32612258, 
        -122.04311589, 
        40.0
      ], 
      "rt": 327.0, 
      "time": 1492073684.0
    }, 
    {
      "pos": [
        37.32611112, 
        -122.04309736, 
        39.0
      ], 
      "rt": 328.0, 
      "time": 1492073685.0
    }, 
    {
      "pos": [
        37.32609715, 
        -122.04308019, 
        40.0
      ], 
      "rt": 329.0, 
      "time": 1492073686.0
    }, 
    {
      "pos": [
        37.32608218, 
        -122.04306374, 
        40.0
      ], 
      "rt": 330.0, 
      "time": 1492073687.0
    }, 
    {
      "pos": [
        37.32606707, 
        -122.04304104, 
        43.0
      ], 
      "rt": 331.0, 
      "time": 1492073688.0
    }, 
    {
      "pos": [
        37.32605188, 
        -122.04301925, 
        43.0
      ], 
      "rt": 332.0, 
      "time": 1492073689.0
    }, 
    {
      "pos": [
        37.32603842, 
        -122.04299952, 
        44.0
      ], 
      "rt": 333.0, 
      "time": 1492073690.0
    }, 
    {
      "pos": [
        37.32602508, 
        -122.04298178, 
        45.0
      ], 
      "rt": 334.0, 
      "time": 1492073691.0
    }, 
    {
      "pos": [
        37.32601258, 
        -122.04296677, 
        45.0
      ], 
      "rt": 335.0, 
      "time": 1492073692.0
    }, 
    {
      "pos": [
        37.32600071, 
        -122.0429501, 
        46.0
      ], 
      "rt": 336.0, 
      "time": 1492073693.0
    }, 
    {
      "pos": [
        37.32598989, 
        -122.04293505, 
        47.0
      ], 
      "rt": 337.0, 
      "time": 1492073694.0
    }, 
    {
      "pos": [
        37.3259789, 
        -122.0429211, 
        46.0
      ], 
      "rt": 338.0, 
      "time": 1492073695.0
    }, 
    {
      "pos": [
        37.32596767, 
        -122.04290754, 
        46.0
      ], 
      "rt": 339.0, 
      "time": 1492073696.0
    }, 
    {
      "pos": [
        37.32595685, 
        -122.04289141, 
        47.0
      ], 
      "rt": 340.0, 
      "time": 1492073697.0
    }, 
    {
      "pos": [
        37.32594629, 
        -122.04287657, 
        47.0
      ], 
      "rt": 341.0, 
      "time": 1492073698.0
    }, 
    {
      "pos": [
        37.32593498, 
        -122.04286212, 
        46.0
      ], 
      "rt": 342.0, 
      "time": 1492073699.0
    }, 
    {
      "pos": [
        37.32592368, 
        -122.04284633, 
        46.0
      ], 
      "rt": 343.0, 
      "time": 1492073700.0
    }, 
    {
      "pos": [
        37.32591224, 
        -122.04282919, 
        46.0
      ], 
      "rt": 344.0, 
      "time": 1492073701.0
    }, 
    {
      "pos": [
        37.32590045, 
        -122.04281341, 
        47.0
      ], 
      "rt": 345.0, 
      "time": 1492073702.0
    }, 
    {
      "pos": [
        37.3258888, 
        -122.04280042, 
        47.0
      ], 
      "rt": 346.0, 
      "time": 1492073703.0
    }, 
    {
      "pos": [
        37.32587724, 
        -122.04278923, 
        47.0
      ], 
      "rt": 347.0, 
      "time": 1492073704.0
    }, 
    {
      "pos": [
        37.32586585, 
        -122.04278095, 
        48.0
      ], 
      "rt": 348.0, 
      "time": 1492073705.0
    }, 
    {
      "pos": [
        37.32585266, 
        -122.04277321, 
        48.0
      ], 
      "rt": 349.0, 
      "time": 1492073706.0
    }, 
    {
      "pos": [
        37.32584098, 
        -122.04276871, 
        48.0
      ], 
      "rt": 350.0, 
      "time": 1492073707.0
    }, 
    {
      "pos": [
        37.32583061, 
        -122.04276782, 
        48.0
      ], 
      "rt": 351.0, 
      "time": 1492073708.0
    }, 
    {
      "pos": [
        37.32582116, 
        -122.04276601, 
        48.0
      ], 
      "rt": 352.0, 
      "time": 1492073709.0
    }, 
    {
      "pos": [
        37.32581301, 
        -122.04276496, 
        48.0
      ], 
      "rt": 353.0, 
      "time": 1492073710.0
    }, 
    {
      "pos": [
        37.32580357, 
        -122.04276614, 
        49.0
      ], 
      "rt": 354.0, 
      "time": 1492073711.0
    }, 
    {
      "pos": [
        37.32579333, 
        -122.04276843, 
        48.0
      ], 
      "rt": 355.0, 
      "time": 1492073712.0
    }, 
    {
      "pos": [
        37.32578045, 
        -122.0427731, 
        49.0
      ], 
      "rt": 356.0, 
      "time": 1492073713.0
    }, 
    {
      "pos": [
        37.32576517, 
        -122.04277794, 
        49.0
      ], 
      "rt": 357.0, 
      "time": 1492073714.0
    }, 
    {
      "pos": [
        37.32575143, 
        -122.04278432, 
        47.0
      ], 
      "rt": 358.0, 
      "time": 1492073715.0
    }, 
    {
      "pos": [
        37.32573571, 
        -122.04279353, 
        48.0
      ], 
      "rt": 359.0, 
      "time": 1492073716.0
    }, 
    {
      "pos": [
        37.3257197, 
        -122.04280577, 
        47.0
      ], 
      "rt": 360.0, 
      "time": 1492073717.0
    }, 
    {
      "pos": [
        37.32570686, 
        -122.04281892, 
        48.0
      ], 
      "rt": 361.0, 
      "time": 1492073718.0
    }, 
    {
      "pos": [
        37.3256956, 
        -122.04283514, 
        48.0
      ], 
      "rt": 362.0, 
      "time": 1492073719.0
    }, 
    {
      "pos": [
        37.32568699, 
        -122.04285169, 
        49.0
      ], 
      "rt": 363.0, 
      "time": 1492073720.0
    }, 
    {
      "pos": [
        37.32567877, 
        -122.04286939, 
        50.0
      ], 
      "rt": 364.0, 
      "time": 1492073721.0
    }, 
    {
      "pos": [
        37.32566888, 
        -122.04288786, 
        51.0
      ], 
      "rt": 365.0, 
      "time": 1492073722.0
    }, 
    {
      "pos": [
        37.32565889, 
        -122.04290477, 
        51.0
      ], 
      "rt": 366.0, 
      "time": 1492073723.0
    }, 
    {
      "pos": [
        37.32564803, 
        -122.04292074, 
        51.0
      ], 
      "rt": 367.0, 
      "time": 1492073724.0
    }, 
    {
      "pos": [
        37.32563706, 
        -122.04293438, 
        51.0
      ], 
      "rt": 368.0, 
      "time": 1492073725.0
    }, 
    {
      "pos": [
        37.32562629, 
        -122.04294703, 
        51.0
      ], 
      "rt": 369.0, 
      "time": 1492073726.0
    }, 
    {
      "pos": [
        37.32561684, 
        -122.0429581, 
        50.0
      ], 
      "rt": 370.0, 
      "time": 1492073727.0
    }, 
    {
      "pos": [
        37.32560588, 
        -122.04296915, 
        50.0
      ], 
      "rt": 371.0, 
      "time": 1492073728.0
    }, 
    {
      "pos": [
        37.32559426, 
        -122.04298189, 
        50.0
      ], 
      "rt": 372.0, 
      "time": 1492073729.0
    }, 
    {
      "pos": [
        37.32558376, 
        -122.04299426, 
        55.0
      ], 
      "rt": 373.0, 
      "time": 1492073730.0
    }, 
    {
      "pos": [
        37.32557436, 
        -122.0430065, 
        54.0
      ], 
      "rt": 374.0, 
      "time": 1492073731.0
    }, 
    {
      "pos": [
        37.32556534, 
        -122.04301744, 
        54.0
      ], 
      "rt": 375.0, 
      "time": 1492073732.0
    }, 
    {
      "pos": [
        37.32555639, 
        -122.04302703, 
        52.0
      ], 
      "rt": 376.0, 
      "time": 1492073733.0
    }, 
    {
      "pos": [
        37.32554869, 
        -122.0430365, 
        52.0
      ], 
      "rt": 377.0, 
      "time": 1492073734.0
    }, 
    {
      "pos": [
        37.32554212, 
        -122.04304499, 
        51.0
      ], 
      "rt": 378.0, 
      "time": 1492073735.0
    }, 
    {
      "pos": [
        37.3255352, 
        -122.04305278, 
        52.0
      ], 
      "rt": 379.0, 
      "time": 1492073736.0
    }, 
    {
      "pos": [
        37.32552618, 
        -122.04306404, 
        52.0
      ], 
      "rt": 380.0, 
      "time": 1492073737.0
    }, 
    {
      "pos": [
        37.32551619, 
        -122.04307746, 
        53.0
      ], 
      "rt": 381.0, 
      "time": 1492073738.0
    }, 
    {
      "pos": [
        37.32550576, 
        -122.04309316, 
        54.0
      ], 
      "rt": 382.0, 
      "time": 1492073739.0
    }, 
    {
      "pos": [
        37.32549771, 
        -122.04311073, 
        54.0
      ], 
      "rt": 383.0, 
      "time": 1492073740.0
    }, 
    {
      "pos": [
        37.3254916, 
        -122.04312717, 
        54.0
      ], 
      "rt": 384.0, 
      "time": 1492073741.0
    }, 
    {
      "pos": [
        37.32548779, 
        -122.04314476, 
        54.0
      ], 
      "rt": 385.0, 
      "time": 1492073742.0
    }, 
    {
      "pos": [
        37.32548301, 
        -122.04316323, 
        54.0
      ], 
      "rt": 386.0, 
      "time": 1492073743.0
    }, 
    {
      "pos": [
        37.32547859, 
        -122.04318128, 
        55.0
      ], 
      "rt": 387.0, 
      "time": 1492073744.0
    }, 
    {
      "pos": [
        37.32547581, 
        -122.04319985, 
        55.0
      ], 
      "rt": 388.0, 
      "time": 1492073745.0
    }, 
    {
      "pos": [
        37.32547497, 
        -122.04321818, 
        56.0
      ], 
      "rt": 389.0, 
      "time": 1492073746.0
    }, 
    {
      "pos": [
        37.32547467, 
        -122.04323258, 
        55.0
      ], 
      "rt": 390.0, 
      "time": 1492073747.0
    }, 
    {
      "pos": [
        37.32547766, 
        -122.04324514, 
        54.0
      ], 
      "rt": 391.0, 
      "time": 1492073748.0
    }, 
    {
      "pos": [
        37.32548122, 
        -122.04325973, 
        57.0
      ], 
      "rt": 392.0, 
      "time": 1492073749.0
    }, 
    {
      "pos": [
        37.32548337, 
        -122.04327649, 
        56.0
      ], 
      "rt": 393.0, 
      "time": 1492073750.0
    }, 
    {
      "pos": [
        37.32548571, 
        -122.04329511, 
        56.0
      ], 
      "rt": 394.0, 
      "time": 1492073751.0
    }, 
    {
      "pos": [
        37.32548641, 
        -122.04331572, 
        57.0
      ], 
      "rt": 395.0, 
      "time": 1492073752.0
    }, 
    {
      "pos": [
        37.3254866, 
        -122.04333609, 
        57.0
      ], 
      "rt": 396.0, 
      "time": 1492073753.0
    }, 
    {
      "pos": [
        37.32548473, 
        -122.04335354, 
        56.0
      ], 
      "rt": 397.0, 
      "time": 1492073754.0
    }, 
    {
      "pos": [
        37.32548389, 
        -122.04336614, 
        55.0
      ], 
      "rt": 398.0, 
      "time": 1492073755.0
    }, 
    {
      "pos": [
        37.32548301, 
        -122.04337832, 
        54.0
      ], 
      "rt": 399.0, 
      "time": 1492073756.0
    }, 
    {
      "pos": [
        37.32548071, 
        -122.04339385, 
        53.0
      ], 
      "rt": 400.0, 
      "time": 1492073757.0
    }, 
    {
      "pos": [
        37.32547724, 
        -122.04340912, 
        52.0
      ], 
      "rt": 401.0, 
      "time": 1492073758.0
    }, 
    {
      "pos": [
        37.32547725, 
        -122.04342251, 
        52.0
      ], 
      "rt": 402.0, 
      "time": 1492073759.0
    }, 
    {
      "pos": [
        37.32547763, 
        -122.04343772, 
        52.0
      ], 
      "rt": 403.0, 
      "time": 1492073760.0
    }, 
    {
      "pos": [
        37.32547885, 
        -122.04345512, 
        52.0
      ], 
      "rt": 404.0, 
      "time": 1492073761.0
    }, 
    {
      "pos": [
        37.32548043, 
        -122.04346852, 
        51.0
      ], 
      "rt": 405.0, 
      "time": 1492073762.0
    }, 
    {
      "pos": [
        37.32548257, 
        -122.04348272, 
        50.0
      ], 
      "rt": 406.0, 
      "time": 1492073763.0
    }, 
    {
      "pos": [
        37.32548416, 
        -122.04350273, 
        50.0
      ], 
      "rt": 407.0, 
      "time": 1492073764.0
    }, 
    {
      "pos": [
        37.32548255, 
        -122.043523, 
        51.0
      ], 
      "rt": 408.0, 
      "time": 1492073765.0
    }, 
    {
      "pos": [
        37.32548079, 
        -122.04354011, 
        51.0
      ], 
      "rt": 409.0, 
      "time": 1492073766.0
    }, 
    {
      "pos": [
        37.3254795, 
        -122.04355658, 
        51.0
      ], 
      "rt": 410.0, 
      "time": 1492073767.0
    }, 
    {
      "pos": [
        37.32547948, 
        -122.0435726, 
        50.0
      ], 
      "rt": 411.0, 
      "time": 1492073768.0
    }, 
    {
      "pos": [
        37.32548256, 
        -122.04358828, 
        50.0
      ], 
      "rt": 412.0, 
      "time": 1492073769.0
    }, 
    {
      "pos": [
        37.32548528, 
        -122.04359724, 
        48.0
      ], 
      "rt": 413.0, 
      "time": 1492073770.0
    }, 
    {
      "pos": [
        37.32548838, 
        -122.04360714, 
        47.0
      ], 
      "rt": 414.0, 
      "time": 1492073771.0
    }, 
    {
      "pos": [
        37.32549167, 
        -122.04362469, 
        48.0
      ], 
      "rt": 415.0, 
      "time": 1492073772.0
    }, 
    {
      "pos": [
        37.32549528, 
        -122.04363827, 
        48.0
      ], 
      "rt": 416.0, 
      "time": 1492073773.0
    }, 
    {
      "pos": [
        37.32549824, 
        -122.04365176, 
        47.0
      ], 
      "rt": 417.0, 
      "time": 1492073774.0
    }, 
    {
      "pos": [
        37.32549906, 
        -122.04367075, 
        48.0
      ], 
      "rt": 418.0, 
      "time": 1492073775.0
    }, 
    {
      "pos": [
        37.32549714, 
        -122.04369004, 
        48.0
      ], 
      "rt": 419.0, 
      "time": 1492073776.0
    }, 
    {
      "pos": [
        37.3254949, 
        -122.04370762, 
        47.0
      ], 
      "rt": 420.0, 
      "time": 1492073777.0
    }, 
    {
      "pos": [
        37.32549376, 
        -122.04372464, 
        47.0
      ], 
      "rt": 421.0, 
      "time": 1492073778.0
    }, 
    {
      "pos": [
        37.32549358, 
        -122.04374273, 
        47.0
      ], 
      "rt": 422.0, 
      "time": 1492073779.0
    }, 
    {
      "pos": [
        37.32549444, 
        -122.04375833, 
        47.0
      ], 
      "rt": 423.0, 
      "time": 1492073780.0
    }, 
    {
      "pos": [
        37.32549379, 
        -122.04377492, 
        48.0
      ], 
      "rt": 424.0, 
      "time": 1492073781.0
    }, 
    {
      "pos": [
        37.3254935, 
        -122.04379582, 
        50.0
      ], 
      "rt": 425.0, 
      "time": 1492073782.0
    }, 
    {
      "pos": [
        37.32549471, 
        -122.04381331, 
        50.0
      ], 
      "rt": 426.0, 
      "time": 1492073783.0
    }, 
    {
      "pos": [
        37.32549826, 
        -122.04382879, 
        49.0
      ], 
      "rt": 427.0, 
      "time": 1492073784.0
    }, 
    {
      "pos": [
        37.3255, 
        -122.04384433, 
        50.0
      ], 
      "rt": 428.0, 
      "time": 1492073785.0
    }, 
    {
      "pos": [
        37.32549939, 
        -122.04386241, 
        50.0
      ], 
      "rt": 429.0, 
      "time": 1492073786.0
    }, 
    {
      "pos": [
        37.32549797, 
        -122.04388134, 
        51.0
      ], 
      "rt": 430.0, 
      "time": 1492073787.0
    }, 
    {
      "pos": [
        37.32549768, 
        -122.04389949, 
        52.0
      ], 
      "rt": 431.0, 
      "time": 1492073788.0
    }, 
    {
      "pos": [
        37.32549834, 
        -122.04391142, 
        52.0
      ], 
      "rt": 432.0, 
      "time": 1492073789.0
    }, 
    {
      "pos": [
        37.3254991, 
        -122.04392919, 
        53.0
      ], 
      "rt": 433.0, 
      "time": 1492073790.0
    }, 
    {
      "pos": [
        37.32549902, 
        -122.04393804, 
        53.0
      ], 
      "rt": 434.0, 
      "time": 1492073791.0
    }, 
    {
      "pos": [
        37.32549935, 
        -122.04394445, 
        53.0
      ], 
      "rt": 435.0, 
      "time": 1492073792.0
    }, 
    {
      "pos": [
        37.32549988, 
        -122.04394745, 
        52.0
      ], 
      "rt": 436.0, 
      "time": 1492073793.0
    }, 
    {
      "pos": [
        37.32549968, 
        -122.04394893, 
        52.0
      ], 
      "rt": 437.0, 
      "time": 1492073794.0
    }, 
    {
      "pos": [
        37.32549919, 
        -122.04394865, 
        52.0
      ], 
      "rt": 438.0, 
      "time": 1492073795.0
    }, 
    {
      "pos": [
        37.32549822, 
        -122.04394902, 
        52.0
      ], 
      "rt": 439.0, 
      "time": 1492073796.0
    }, 
    {
      "pos": [
        37.32549738, 
        -122.04394846, 
        51.0
      ], 
      "rt": 440.0, 
      "time": 1492073797.0
    }, 
    {
      "pos": [
        37.32549732, 
        -122.04395382, 
        51.0
      ], 
      "rt": 441.0, 
      "time": 1492073798.0
    }, 
    {
      "pos": [
        37.32549783, 
        -122.04396111, 
        51.0
      ], 
      "rt": 442.0, 
      "time": 1492073799.0
    }, 
    {
      "pos": [
        37.32549794, 
        -122.04396357, 
        51.0
      ], 
      "rt": 443.0, 
      "time": 1492073800.0
    }, 
    {
      "pos": [
        37.32549791, 
        -122.04396238, 
        51.0
      ], 
      "rt": 444.0, 
      "time": 1492073801.0
    }, 
    {
      "pos": [
        37.32549658, 
        -122.04396378, 
        52.0
      ], 
      "rt": 445.0, 
      "time": 1492073802.0
    }, 
    {
      "pos": [
        37.32549628, 
        -122.04396502, 
        51.0
      ], 
      "rt": 446.0, 
      "time": 1492073803.0
    }, 
    {
      "pos": [
        37.32549632, 
        -122.04396571, 
        51.0
      ], 
      "rt": 447.0, 
      "time": 1492073804.0
    }, 
    {
      "pos": [
        37.32549635, 
        -122.0439652, 
        51.0
      ], 
      "rt": 448.0, 
      "time": 1492073805.0
    }, 
    {
      "pos": [
        37.32549678, 
        -122.04396624, 
        51.0
      ], 
      "rt": 449.0, 
      "time": 1492073806.0
    }, 
    {
      "pos": [
        37.32549809, 
        -122.04396596, 
        51.0
      ], 
      "rt": 450.0, 
      "time": 1492073807.0
    }, 
    {
      "pos": [
        37.32549842, 
        -122.04396586, 
        51.0
      ], 
      "rt": 451.0, 
      "time": 1492073808.0
    }, 
    {
      "pos": [
        37.32549883, 
        -122.04396539, 
        51.0
      ], 
      "rt": 452.0, 
      "time": 1492073809.0
    }, 
    {
      "pos": [
        37.32549955, 
        -122.04396491, 
        51.0
      ], 
      "rt": 453.0, 
      "time": 1492073810.0
    }, 
    {
      "pos": [
        37.3254999, 
        -122.04396465, 
        51.0
      ], 
      "rt": 454.0, 
      "time": 1492073811.0
    }, 
    {
      "pos": [
        37.3255003, 
        -122.04396386, 
        51.0
      ], 
      "rt": 455.0, 
      "time": 1492073812.0
    }, 
    {
      "pos": [
        37.32550029, 
        -122.04396633, 
        52.0
      ], 
      "rt": 456.0, 
      "time": 1492073813.0
    }, 
    {
      "pos": [
        37.32550053, 
        -122.04397125, 
        52.0
      ], 
      "rt": 457.0, 
      "time": 1492073814.0
    }, 
    {
      "pos": [
        37.32550111, 
        -122.04398158, 
        52.0
      ], 
      "rt": 458.0, 
      "time": 1492073815.0
    }, 
    {
      "pos": [
        37.32550134, 
        -122.04399498, 
        52.0
      ], 
      "rt": 459.0, 
      "time": 1492073816.0
    }, 
    {
      "pos": [
        37.32550196, 
        -122.04400765, 
        52.0
      ], 
      "rt": 460.0, 
      "time": 1492073817.0
    }, 
    {
      "pos": [
        37.32550276, 
        -122.04402085, 
        52.0
      ], 
      "rt": 461.0, 
      "time": 1492073818.0
    }, 
    {
      "pos": [
        37.32550281, 
        -122.04403415, 
        52.0
      ], 
      "rt": 462.0, 
      "time": 1492073819.0
    }, 
    {
      "pos": [
        37.32550332, 
        -122.0440471, 
        52.0
      ], 
      "rt": 463.0, 
      "time": 1492073820.0
    }, 
    {
      "pos": [
        37.32550331, 
        -122.04405986, 
        52.0
      ], 
      "rt": 464.0, 
      "time": 1492073821.0
    }, 
    {
      "pos": [
        37.32550277, 
        -122.04407292, 
        52.0
      ], 
      "rt": 465.0, 
      "time": 1492073822.0
    }, 
    {
      "pos": [
        37.3255036, 
        -122.04408287, 
        51.0
      ], 
      "rt": 466.0, 
      "time": 1492073823.0
    }, 
    {
      "pos": [
        37.32550237, 
        -122.0440905, 
        51.0
      ], 
      "rt": 467.0, 
      "time": 1492073824.0
    }, 
    {
      "pos": [
        37.32549909, 
        -122.04410258, 
        52.0
      ], 
      "rt": 468.0, 
      "time": 1492073825.0
    }, 
    {
      "pos": [
        37.3254933, 
        -122.04411065, 
        51.0
      ], 
      "rt": 469.0, 
      "time": 1492073826.0
    }, 
    {
      "pos": [
        37.32548405, 
        -122.04411823, 
        52.0
      ], 
      "rt": 470.0, 
      "time": 1492073827.0
    }, 
    {
      "pos": [
        37.32547167, 
        -122.04412735, 
        53.0
      ], 
      "rt": 471.0, 
      "time": 1492073828.0
    }, 
    {
      "pos": [
        37.32545883, 
        -122.04413587, 
        53.0
      ], 
      "rt": 472.0, 
      "time": 1492073829.0
    }, 
    {
      "pos": [
        37.32544609, 
        -122.04414468, 
        54.0
      ], 
      "rt": 473.0, 
      "time": 1492073830.0
    }, 
    {
      "pos": [
        37.32543432, 
        -122.04415287, 
        53.0
      ], 
      "rt": 474.0, 
      "time": 1492073831.0
    }, 
    {
      "pos": [
        37.32542114, 
        -122.04416067, 
        53.0
      ], 
      "rt": 475.0, 
      "time": 1492073832.0
    }, 
    {
      "pos": [
        37.32540736, 
        -122.0441682, 
        53.0
      ], 
      "rt": 476.0, 
      "time": 1492073833.0
    }, 
    {
      "pos": [
        37.32539307, 
        -122.04417563, 
        53.0
      ], 
      "rt": 477.0, 
      "time": 1492073834.0
    }, 
    {
      "pos": [
        37.32537915, 
        -122.04418416, 
        53.0
      ], 
      "rt": 478.0, 
      "time": 1492073835.0
    }, 
    {
      "pos": [
        37.32536786, 
        -122.04419216, 
        53.0
      ], 
      "rt": 479.0, 
      "time": 1492073836.0
    }, 
    {
      "pos": [
        37.32535743, 
        -122.04419656, 
        51.0
      ], 
      "rt": 480.0, 
      "time": 1492073837.0
    }, 
    {
      "pos": [
        37.32534909, 
        -122.04420054, 
        52.0
      ], 
      "rt": 481.0, 
      "time": 1492073838.0
    }, 
    {
      "pos": [
        37.32533979, 
        -122.04420206, 
        50.0
      ], 
      "rt": 482.0, 
      "time": 1492073839.0
    }, 
    {
      "pos": [
        37.32532952, 
        -122.04420616, 
        51.0
      ], 
      "rt": 483.0, 
      "time": 1492073840.0
    }, 
    {
      "pos": [
        37.32531642, 
        -122.04421082, 
        50.0
      ], 
      "rt": 484.0, 
      "time": 1492073841.0
    }, 
    {
      "pos": [
        37.32530364, 
        -122.04421977, 
        51.0
      ], 
      "rt": 485.0, 
      "time": 1492073842.0
    }, 
    {
      "pos": [
        37.32529061, 
        -122.04422781, 
        51.0
      ], 
      "rt": 486.0, 
      "time": 1492073843.0
    }, 
    {
      "pos": [
        37.32528024, 
        -122.04423479, 
        50.0
      ], 
      "rt": 487.0, 
      "time": 1492073844.0
    }, 
    {
      "pos": [
        37.32527128, 
        -122.04424125, 
        50.0
      ], 
      "rt": 488.0, 
      "time": 1492073845.0
    }, 
    {
      "pos": [
        37.32526252, 
        -122.04424739, 
        49.0
      ], 
      "rt": 489.0, 
      "time": 1492073846.0
    }, 
    {
      "pos": [
        37.32525425, 
        -122.04425369, 
        49.0
      ], 
      "rt": 490.0, 
      "time": 1492073847.0
    }, 
    {
      "pos": [
        37.32524589, 
        -122.04426231, 
        49.0
      ], 
      "rt": 491.0, 
      "time": 1492073848.0
    }, 
    {
      "pos": [
        37.32524012, 
        -122.0442705, 
        50.0
      ], 
      "rt": 492.0, 
      "time": 1492073849.0
    }, 
    {
      "pos": [
        37.3252331, 
        -122.04427889, 
        49.0
      ], 
      "rt": 493.0, 
      "time": 1492073850.0
    }, 
    {
      "pos": [
        37.32522406, 
        -122.04429003, 
        49.0
      ], 
      "rt": 494.0, 
      "time": 1492073851.0
    }, 
    {
      "pos": [
        37.32521537, 
        -122.04430159, 
        48.0
      ], 
      "rt": 495.0, 
      "time": 1492073852.0
    }, 
    {
      "pos": [
        37.32520766, 
        -122.04431408, 
        47.0
      ], 
      "rt": 496.0, 
      "time": 1492073853.0
    }, 
    {
      "pos": [
        37.32520038, 
        -122.0443268, 
        48.0
      ], 
      "rt": 497.0, 
      "time": 1492073854.0
    }, 
    {
      "pos": [
        37.32519353, 
        -122.04433935, 
        47.0
      ], 
      "rt": 498.0, 
      "time": 1492073855.0
    }, 
    {
      "pos": [
        37.32518488, 
        -122.044352, 
        47.0
      ], 
      "rt": 499.0, 
      "time": 1492073856.0
    }, 
    {
      "pos": [
        37.32517705, 
        -122.04436295, 
        47.0
      ], 
      "rt": 500.0, 
      "time": 1492073857.0
    }, 
    {
      "pos": [
        37.32516867, 
        -122.04437384, 
        47.0
      ], 
      "rt": 501.0, 
      "time": 1492073858.0
    }, 
    {
      "pos": [
        37.32515977, 
        -122.04438564, 
        47.0
      ], 
      "rt": 502.0, 
      "time": 1492073859.0
    }, 
    {
      "pos": [
        37.32515108, 
        -122.04439741, 
        47.0
      ], 
      "rt": 503.0, 
      "time": 1492073860.0
    }, 
    {
      "pos": [
        37.32514425, 
        -122.04440725, 
        47.0
      ], 
      "rt": 504.0, 
      "time": 1492073861.0
    }, 
    {
      "pos": [
        37.32513749, 
        -122.04442004, 
        47.0
      ], 
      "rt": 505.0, 
      "time": 1492073862.0
    }, 
    {
      "pos": [
        37.32513142, 
        -122.0444334, 
        46.0
      ], 
      "rt": 506.0, 
      "time": 1492073863.0
    }, 
    {
      "pos": [
        37.32512779, 
        -122.0444467, 
        46.0
      ], 
      "rt": 507.0, 
      "time": 1492073864.0
    }, 
    {
      "pos": [
        37.32512563, 
        -122.04446099, 
        46.0
      ], 
      "rt": 508.0, 
      "time": 1492073865.0
    }, 
    {
      "pos": [
        37.32512434, 
        -122.04447536, 
        47.0
      ], 
      "rt": 509.0, 
      "time": 1492073866.0
    }, 
    {
      "pos": [
        37.3251227, 
        -122.0444929, 
        47.0
      ], 
      "rt": 510.0, 
      "time": 1492073867.0
    }, 
    {
      "pos": [
        37.32512036, 
        -122.04451193, 
        47.0
      ], 
      "rt": 511.0, 
      "time": 1492073868.0
    }, 
    {
      "pos": [
        37.32511886, 
        -122.04453086, 
        47.0
      ], 
      "rt": 512.0, 
      "time": 1492073869.0
    }, 
    {
      "pos": [
        37.32511811, 
        -122.04454872, 
        46.0
      ], 
      "rt": 513.0, 
      "time": 1492073870.0
    }, 
    {
      "pos": [
        37.32511691, 
        -122.04456663, 
        47.0
      ], 
      "rt": 514.0, 
      "time": 1492073871.0
    }, 
    {
      "pos": [
        37.32511513, 
        -122.0445853, 
        47.0
      ], 
      "rt": 515.0, 
      "time": 1492073872.0
    }, 
    {
      "pos": [
        37.32511366, 
        -122.04460233, 
        46.0
      ], 
      "rt": 516.0, 
      "time": 1492073873.0
    }, 
    {
      "pos": [
        37.32511119, 
        -122.04461847, 
        46.0
      ], 
      "rt": 517.0, 
      "time": 1492073874.0
    }, 
    {
      "pos": [
        37.32510771, 
        -122.04463489, 
        47.0
      ], 
      "rt": 518.0, 
      "time": 1492073875.0
    }, 
    {
      "pos": [
        37.32510362, 
        -122.04465059, 
        47.0
      ], 
      "rt": 519.0, 
      "time": 1492073876.0
    }, 
    {
      "pos": [
        37.32509849, 
        -122.04466521, 
        46.0
      ], 
      "rt": 520.0, 
      "time": 1492073877.0
    }, 
    {
      "pos": [
        37.32509233, 
        -122.04467915, 
        46.0
      ], 
      "rt": 521.0, 
      "time": 1492073878.0
    }, 
    {
      "pos": [
        37.32508553, 
        -122.04469219, 
        46.0
      ], 
      "rt": 522.0, 
      "time": 1492073879.0
    }, 
    {
      "pos": [
        37.32507853, 
        -122.04470522, 
        46.0
      ], 
      "rt": 523.0, 
      "time": 1492073880.0
    }, 
    {
      "pos": [
        37.32507173, 
        -122.04471926, 
        46.0
      ], 
      "rt": 524.0, 
      "time": 1492073881.0
    }, 
    {
      "pos": [
        37.32506534, 
        -122.04473315, 
        46.0
      ], 
      "rt": 525.0, 
      "time": 1492073882.0
    }, 
    {
      "pos": [
        37.32506065, 
        -122.04474869, 
        46.0
      ], 
      "rt": 526.0, 
      "time": 1492073883.0
    }, 
    {
      "pos": [
        37.32505885, 
        -122.04476324, 
        45.0
      ], 
      "rt": 527.0, 
      "time": 1492073884.0
    }, 
    {
      "pos": [
        37.32505787, 
        -122.0447802, 
        46.0
      ], 
      "rt": 528.0, 
      "time": 1492073885.0
    }, 
    {
      "pos": [
        37.32505601, 
        -122.04480042, 
        47.0
      ], 
      "rt": 529.0, 
      "time": 1492073886.0
    }, 
    {
      "pos": [
        37.32505482, 
        -122.04481982, 
        48.0
      ], 
      "rt": 530.0, 
      "time": 1492073887.0
    }, 
    {
      "pos": [
        37.32505387, 
        -122.04483964, 
        48.0
      ], 
      "rt": 531.0, 
      "time": 1492073888.0
    }, 
    {
      "pos": [
        37.32505373, 
        -122.04485992, 
        48.0
      ], 
      "rt": 532.0, 
      "time": 1492073889.0
    }, 
    {
      "pos": [
        37.32505347, 
        -122.04488002, 
        48.0
      ], 
      "rt": 533.0, 
      "time": 1492073890.0
    }, 
    {
      "pos": [
        37.32505232, 
        -122.04489914, 
        48.0
      ], 
      "rt": 534.0, 
      "time": 1492073891.0
    }, 
    {
      "pos": [
        37.3250515, 
        -122.04491597, 
        48.0
      ], 
      "rt": 535.0, 
      "time": 1492073892.0
    }, 
    {
      "pos": [
        37.32505133, 
        -122.04493311, 
        49.0
      ], 
      "rt": 536.0, 
      "time": 1492073893.0
    }, 
    {
      "pos": [
        37.3250512, 
        -122.04495166, 
        50.0
      ], 
      "rt": 537.0, 
      "time": 1492073894.0
    }, 
    {
      "pos": [
        37.32505122, 
        -122.04497005, 
        50.0
      ], 
      "rt": 538.0, 
      "time": 1492073895.0
    }, 
    {
      "pos": [
        37.32505263, 
        -122.04498826, 
        50.0
      ], 
      "rt": 539.0, 
      "time": 1492073896.0
    }, 
    {
      "pos": [
        37.32505472, 
        -122.04500725, 
        51.0
      ], 
      "rt": 540.0, 
      "time": 1492073897.0
    }, 
    {
      "pos": [
        37.32505837, 
        -122.04502543, 
        51.0
      ], 
      "rt": 541.0, 
      "time": 1492073898.0
    }, 
    {
      "pos": [
        37.32506351, 
        -122.04504367, 
        51.0
      ], 
      "rt": 542.0, 
      "time": 1492073899.0
    }, 
    {
      "pos": [
        37.3250703, 
        -122.04506094, 
        51.0
      ], 
      "rt": 543.0, 
      "time": 1492073900.0
    }, 
    {
      "pos": [
        37.32507729, 
        -122.04507727, 
        51.0
      ], 
      "rt": 544.0, 
      "time": 1492073901.0
    }, 
    {
      "pos": [
        37.32508471, 
        -122.04509226, 
        51.0
      ], 
      "rt": 545.0, 
      "time": 1492073902.0
    }, 
    {
      "pos": [
        37.32509263, 
        -122.04510639, 
        51.0
      ], 
      "rt": 546.0, 
      "time": 1492073903.0
    }, 
    {
      "pos": [
        37.32510044, 
        -122.04512053, 
        51.0
      ], 
      "rt": 547.0, 
      "time": 1492073904.0
    }, 
    {
      "pos": [
        37.32510766, 
        -122.04513432, 
        49.0
      ], 
      "rt": 548.0, 
      "time": 1492073905.0
    }, 
    {
      "pos": [
        37.32511354, 
        -122.04514817, 
        49.0
      ], 
      "rt": 549.0, 
      "time": 1492073906.0
    }, 
    {
      "pos": [
        37.32511867, 
        -122.04516229, 
        49.0
      ], 
      "rt": 550.0, 
      "time": 1492073907.0
    }, 
    {
      "pos": [
        37.32512312, 
        -122.04517833, 
        50.0
      ], 
      "rt": 551.0, 
      "time": 1492073908.0
    }, 
    {
      "pos": [
        37.32512624, 
        -122.04519639, 
        50.0
      ], 
      "rt": 552.0, 
      "time": 1492073909.0
    }, 
    {
      "pos": [
        37.32512834, 
        -122.04521509, 
        50.0
      ], 
      "rt": 553.0, 
      "time": 1492073910.0
    }, 
    {
      "pos": [
        37.32512865, 
        -122.04523361, 
        50.0
      ], 
      "rt": 554.0, 
      "time": 1492073911.0
    }, 
    {
      "pos": [
        37.32513023, 
        -122.04525146, 
        50.0
      ], 
      "rt": 555.0, 
      "time": 1492073912.0
    }, 
    {
      "pos": [
        37.32513285, 
        -122.04526909, 
        50.0
      ], 
      "rt": 556.0, 
      "time": 1492073913.0
    }, 
    {
      "pos": [
        37.32513541, 
        -122.04528702, 
        50.0
      ], 
      "rt": 557.0, 
      "time": 1492073914.0
    }, 
    {
      "pos": [
        37.32513431, 
        -122.04530612, 
        50.0
      ], 
      "rt": 558.0, 
      "time": 1492073915.0
    }, 
    {
      "pos": [
        37.32513069, 
        -122.0453262, 
        50.0
      ], 
      "rt": 559.0, 
      "time": 1492073916.0
    }, 
    {
      "pos": [
        37.32512707, 
        -122.0453474, 
        50.0
      ], 
      "rt": 560.0, 
      "time": 1492073917.0
    }, 
    {
      "pos": [
        37.32512367, 
        -122.04536815, 
        50.0
      ], 
      "rt": 561.0, 
      "time": 1492073918.0
    }, 
    {
      "pos": [
        37.3251201, 
        -122.04538847, 
        50.0
      ], 
      "rt": 562.0, 
      "time": 1492073919.0
    }, 
    {
      "pos": [
        37.32511831, 
        -122.04540756, 
        49.0
      ], 
      "rt": 563.0, 
      "time": 1492073920.0
    }, 
    {
      "pos": [
        37.32511743, 
        -122.04542584, 
        50.0
      ], 
      "rt": 564.0, 
      "time": 1492073921.0
    }, 
    {
      "pos": [
        37.32511721, 
        -122.04544386, 
        49.0
      ], 
      "rt": 565.0, 
      "time": 1492073922.0
    }, 
    {
      "pos": [
        37.32511576, 
        -122.04546019, 
        49.0
      ], 
      "rt": 566.0, 
      "time": 1492073923.0
    }, 
    {
      "pos": [
        37.32511371, 
        -122.0454744, 
        49.0
      ], 
      "rt": 567.0, 
      "time": 1492073924.0
    }, 
    {
      "pos": [
        37.32511128, 
        -122.04548485, 
        49.0
      ], 
      "rt": 568.0, 
      "time": 1492073925.0
    }, 
    {
      "pos": [
        37.32510926, 
        -122.04548888, 
        49.0
      ], 
      "rt": 569.0, 
      "time": 1492073926.0
    }, 
    {
      "pos": [
        37.32510774, 
        -122.0454898, 
        49.0
      ], 
      "rt": 570.0, 
      "time": 1492073927.0
    }, 
    {
      "pos": [
        37.32510677, 
        -122.04548945, 
        49.0
      ], 
      "rt": 571.0, 
      "time": 1492073928.0
    }, 
    {
      "pos": [
        37.32510496, 
        -122.04548682, 
        50.0
      ], 
      "rt": 572.0, 
      "time": 1492073929.0
    }, 
    {
      "pos": [
        37.32510448, 
        -122.04548434, 
        50.0
      ], 
      "rt": 573.0, 
      "time": 1492073930.0
    }, 
    {
      "pos": [
        37.3251036, 
        -122.04548358, 
        51.0
      ], 
      "rt": 574.0, 
      "time": 1492073931.0
    }, 
    {
      "pos": [
        37.32510263, 
        -122.0454815, 
        50.0
      ], 
      "rt": 575.0, 
      "time": 1492073932.0
    }, 
    {
      "pos": [
        37.32510214, 
        -122.04547964, 
        51.0
      ], 
      "rt": 576.0, 
      "time": 1492073933.0
    }, 
    {
      "pos": [
        37.3251007, 
        -122.04547997, 
        52.0
      ], 
      "rt": 577.0, 
      "time": 1492073934.0
    }, 
    {
      "pos": [
        37.32509937, 
        -122.04547882, 
        51.0
      ], 
      "rt": 578.0, 
      "time": 1492073935.0
    }, 
    {
      "pos": [
        37.32509832, 
        -122.04547788, 
        51.0
      ], 
      "rt": 579.0, 
      "time": 1492073936.0
    }, 
    {
      "pos": [
        37.32509806, 
        -122.04547742, 
        51.0
      ], 
      "rt": 580.0, 
      "time": 1492073937.0
    }, 
    {
      "pos": [
        37.32509852, 
        -122.04547774, 
        51.0
      ], 
      "rt": 581.0, 
      "time": 1492073938.0
    }, 
    {
      "pos": [
        37.32509879, 
        -122.04547858, 
        51.0
      ], 
      "rt": 582.0, 
      "time": 1492073939.0
    }, 
    {
      "pos": [
        37.32509901, 
        -122.04547925, 
        51.0
      ], 
      "rt": 583.0, 
      "time": 1492073940.0
    }, 
    {
      "pos": [
        37.32509906, 
        -122.04547977, 
        51.0
      ], 
      "rt": 584.0, 
      "time": 1492073941.0
    }, 
    {
      "pos": [
        37.32509911, 
        -122.04548012, 
        51.0
      ], 
      "rt": 585.0, 
      "time": 1492073942.0
    }, 
    {
      "pos": [
        37.32509914, 
        -122.04548032, 
        51.0
      ], 
      "rt": 586.0, 
      "time": 1492073943.0
    }, 
    {
      "pos": [
        37.32509915, 
        -122.04548045, 
        51.0
      ], 
      "rt": 587.0, 
      "time": 1492073944.0
    }, 
    {
      "pos": [
        37.32509915, 
        -122.04548053, 
        51.0
      ], 
      "rt": 588.0, 
      "time": 1492073945.0
    }, 
    {
      "pos": [
        37.32509914, 
        -122.04548058, 
        51.0
      ], 
      "rt": 589.0, 
      "time": 1492073946.0
    }, 
    {
      "pos": [
        37.32509913, 
        -122.0454806, 
        51.0
      ], 
      "rt": 590.0, 
      "time": 1492073947.0
    }, 
    {
      "pos": [
        37.32509912, 
        -122.04548063, 
        51.0
      ], 
      "rt": 591.0, 
      "time": 1492073948.0
    }, 
    {
      "pos": [
        37.32509911, 
        -122.04548066, 
        51.0
      ], 
      "rt": 592.0, 
      "time": 1492073949.0
    }, 
    {
      "pos": [
        37.32509908, 
        -122.0454807, 
        51.0
      ], 
      "rt": 593.0, 
      "time": 1492073950.0
    }, 
    {
      "pos": [
        37.32509905, 
        -122.04548074, 
        51.0
      ], 
      "rt": 594.0, 
      "time": 1492073951.0
    }, 
    {
      "pos": [
        37.32509904, 
        -122.04548077, 
        51.0
      ], 
      "rt": 595.0, 
      "time": 1492073952.0
    }, 
    {
      "pos": [
        37.32509903, 
        -122.04548082, 
        51.0
      ], 
      "rt": 596.0, 
      "time": 1492073953.0
    }
  ], 
  "startTime": 1492073357.0
}
